jinjasql/__init__.py
jinjasql/core.py
jinjasql_m-0.1.22.dist-info/LICENSE
jinjasql_m-0.1.22.dist-info/METADATA
jinjasql_m-0.1.22.dist-info/WHEEL
jinjasql_m-0.1.22.dist-info/top_level.txt
jinjasql_m-0.1.22.dist-info/RECORD
