Metadata-Version: 2.1
Name: jinjasql-m
Version: 0.1.22
Summary: Generate SQL Queries and Corresponding Bind Parameters using a Jinja2 Template
Home-page: https://github.com/sripathikrishnan/jinjasql
Download-URL: http://cloud.github.com/downloads/sripathikrishnan/jinjasql/jinjasql-0.1.22.tar.gz
Author: Sripathi Krishnan
Author-email: Sripathi.Krishnan@gmail.com
Maintainer: Sripathi Krishnan
Maintainer-email: Sripathi.Krishnan@gmail.com
License: MIT
Keywords: Jinja2,SQL,Python,Template
Classifier: Development Status :: 4 - Beta
Classifier: Environment :: Console
Classifier: Intended Audience :: Developers
Classifier: License :: OSI Approved :: MIT License
Classifier: Operating System :: OS Independent
Classifier: Programming Language :: Python
Classifier: Programming Language :: Python :: 2.7
Classifier: Programming Language :: Python :: 3
Classifier: Programming Language :: Python :: 3.3
Classifier: Programming Language :: Python :: 3.4
Classifier: Programming Language :: Python :: 3.5
License-File: LICENSE
Requires-Dist: Jinja2 (==3.1.4)
